<!--<?xml version="1.0" encoding="UTF-8"?>-->
<!--<!DOCTYPE beans PUBLIC "-//SPRING//DTD BEAN 2.0//EN" "http://www.springframework.org/dtd/spring-beans-2.0.dtd">-->
<!--<beans>-->
<!--	<import resource="classpath:org/codehaus/xfire/spring/xfire.xml" />-->
<!--	-->
<!--	<bean id="baseWebService" class="org.codehaus.xfire.spring.remoting.XFireExporter" lazy-init="false" abstract="true">-->
<!--		<property name="serviceFactory" ref="xfire.serviceFactory" />-->
<!--		<property name="xfire" ref="xfire" />    -->
<!--	</bean>-->
	
<!--	<bean id="sysOperatorService" parent="baseWebService">-->
		<!-- 服务接口实现类 -->
<!--		<property name="serviceBean" ref="sysOperatorManage" />-->
		<!-- 服务接口，客户端部署时需要 -->
<!--		<property name="serviceClass" value="com.whmetro.systemmanage.sysmaintain.xfire.SysOperatorService" />-->
<!--	</bean>-->

<!--</beans>-->

